APACHE-LICENSE-2.0.txt
CHANGELOG.rst
LICENSE
MANIFEST.in
README.rst
setup.py
doc/Makefile
doc/changelog.rst
doc/conf.py
doc/doc_djangosettings.py
doc/existdb.rst
doc/index.rst
pyexistdb/__init__.py
pyexistdb/db.py
pyexistdb/debug_panel.py
pyexistdb/exceptions.py
pyexistdb/manager.py
pyexistdb/models.py
pyexistdb/patch.py
pyexistdb/query.py
pyexistdb/testutil.py
pyexistdb.egg-info/PKG-INFO
pyexistdb.egg-info/SOURCES.txt
pyexistdb.egg-info/dependency_links.txt
pyexistdb.egg-info/requires.txt
pyexistdb.egg-info/top_level.txt
pyexistdb/management/__init__.py
pyexistdb/management/commands/__init__.py
pyexistdb/management/commands/existdb.py
pyexistdb/templatetags/__init__.py
pyexistdb/templatetags/existdb.py
test/localsettings.py
test/test_existdb/__init__.py
test/test_existdb/test_db.py
test/test_existdb/test_exceptions.py
test/test_existdb/test_models.py
test/test_existdb/test_patch.py
test/test_existdb/test_query.py
test/test_existdb/test_templatetags.py
test/test_existdb/exist_fixtures/goodbye-english.xml
test/test_existdb/exist_fixtures/goodbye-french.xml
test/test_existdb/exist_fixtures/hello.xml