Metadata-Version: 1.1
Name: pyexistdb
Version: 1.0.1
Summary: Idiomatic access to the eXist-db XML Database using XPath and XQuery
Home-page: https://github.com/zmbq/pyexistdb
Author: The Research Software Company
Author-email: contact@chelem.co.il
License: Apache License, Version 2.0
Keywords: eXist-db XQuery
Platform: UNKNOWN
Classifier: Development Status :: 4 - Beta
Classifier: Framework :: Django
Classifier: Intended Audience :: Developers
Classifier: License :: OSI Approved :: Apache Software License
Classifier: Natural Language :: English
Classifier: Operating System :: OS Independent
Classifier: Programming Language :: Python
Classifier: Topic :: Software Development :: Libraries :: Python Modules
Classifier: Topic :: Text Processing :: Markup :: XML
